{"stats":{"minecraft:custom":{"minecraft:time_since_rest":3357,"minecraft:crouch_one_cm":100,"minecraft:play_time":3357,"minecraft:sprint_one_cm":6913,"minecraft:damage_taken":194,"minecraft:walk_one_cm":1935,"minecraft:sneak_time":17,"minecraft:mob_kills":7,"minecraft:jump":38,"minecraft:damage_dealt":200,"minecraft:leave_game":1,"minecraft:time_since_death":3357,"minecraft:total_world_time":3382,"minecraft:fly_one_cm":11709,"minecraft:fall_one_cm":836},"minecraft:mined":{"minecraft:fern":1},"minecraft:picked_up":{"minecraft:egg":1},"minecraft:killed":{"minecraft:chicken":3,"minecraft:cow":4},"minecraft:used":{"minecraft:trident":16,"minecraft:cooked_porkchop":1,"minecraft:netherite_axe":3,"minecraft:egg":1,"minecraft:lingering_potion":1,"minecraft:splash_potion":3}},"DataVersion":3120}